test_automation/__init__.py
test_automation/api.py
test_automation/dispatch.py
test_automation/gowin.py
test_automation/hubyo.py
test_automation/log.py
test_automation/orderyo.py
test_automation/rider.py
test_automation/ui.py
test_automation/ui_funtions.py
test_automation/vault.py
test_automation-0.1.7.dist-info/LICENSE
test_automation-0.1.7.dist-info/METADATA
test_automation-0.1.7.dist-info/WHEEL
test_automation-0.1.7.dist-info/RECORD
