Metadata-Version: 2.1
Name: test-automation
Version: 0.1.7
Summary: test framework for yogiyo
Author: KimKitaeB
Author-email: kt.kim@wesang.com
Requires-Python: >=3.10,<4.0
Classifier: Programming Language :: Python :: 3
Classifier: Programming Language :: Python :: 3.10
Classifier: Programming Language :: Python :: 3.11
Requires-Dist: appium-python-client (>=2.7.1,<3.0.0)
Requires-Dist: pytest (>=7.2.0,<8.0.0)
Requires-Dist: requests (>=2.28.1,<3.0.0)
Requires-Dist: selenium (>=4.5.0,<5.0.0)
